README.md
setup.py
flaskrouting/__init__.py
flaskrouting.egg-info/PKG-INFO
flaskrouting.egg-info/SOURCES.txt
flaskrouting.egg-info/dependency_links.txt
flaskrouting.egg-info/top_level.txt