Metadata-Version: 2.1
Name: flaskrouting
Version: 1.0
Summary: Create simple, nestable routes in flask.
Home-page: https://github.com/Kangaroux/flaskrouting
Author: kangaroux
Author-email: roux.jesse@gmail.com
License: MIT
Platform: UNKNOWN
